[
  {
    "userId": 1733671122532,
    "longitude": 234234324,
    "latitude": 3232343223,
    "timestamp": "heyeye",
    "deviceName": "SherHondai"
  },
  {
    "userId": 1733758536521,
    "longitude": 74.2580978,
    "latitude": 31.5089871,
    "timestamp": "12/9/2024, 8:57:59 PM",
    "deviceName": "Tecno spark"
  },
  {
    "userId": 1733758536521,
    "longitude": 74.2580978,
    "latitude": 31.5089871,
    "timestamp": "12/9/2024, 8:59:28 PM",
    "deviceName": "Hwawie"
  },
  {
    "userId": 1733671122532,
    "longitude": 74.2580978,
    "latitude": 31.5089871,
    "timestamp": "12/9/2024, 9:00:24 PM",
    "deviceName": "iphone steck"
  }
]